RPA_Windows.libspec
RPA/scripts/record.py
RPA/Windows/__init__.py
RPA/Windows/__main__.py
RPA/Windows/keywords/__init__.py
RPA/Windows/keywords/action.py
RPA/Windows/keywords/context.py
RPA/Windows/keywords/elements.py
RPA/Windows/keywords/locators.py
RPA/Windows/keywords/window.py
RPA/Windows/main.py
RPA/Windows/utils.py
rpaframework_windows-8.0.0.dist-info/entry_points.txt
rpaframework_windows-8.0.0.dist-info/LICENSE
rpaframework_windows-8.0.0.dist-info/METADATA
rpaframework_windows-8.0.0.dist-info/WHEEL
rpaframework_windows-8.0.0.dist-info/RECORD
