Metadata-Version: 2.1
Name: rpaframework-windows
Version: 8.0.0
Summary: Windows library for RPA Framework
Home-page: https://rpaframework.org/
License: Apache-2.0
Keywords: robotframework,rpa,automation,windows,uiautomation
Author: RPA Framework
Author-email: rpafw@robocorp.com
Requires-Python: >=3.9,<4.0
Classifier: Development Status :: 5 - Production/Stable
Classifier: Framework :: Robot Framework
Classifier: Framework :: Robot Framework :: Library
Classifier: Intended Audience :: Developers
Classifier: License :: OSI Approved :: Apache Software License
Classifier: Operating System :: Microsoft :: Windows
Classifier: Programming Language :: Python :: 3
Classifier: Programming Language :: Python :: 3.9
Classifier: Programming Language :: Python :: 3.10
Classifier: Programming Language :: Python :: 3.11
Classifier: Programming Language :: Python :: 3.12
Classifier: Topic :: Software Development :: Libraries
Classifier: Topic :: Software Development :: Libraries :: Python Modules
Requires-Dist: comtypes (>=1.1.11,<2.0.0) ; sys_platform == "win32"
Requires-Dist: dataclasses (>=0.7,<0.8) ; python_version >= "3.6" and python_version < "3.7"
Requires-Dist: fire (>=0.7.0,<0.8.0)
Requires-Dist: psutil (>=5.9.0,<6.0.0) ; sys_platform == "win32"
Requires-Dist: pynput-robocorp-fork (>=5.0.0,<6.0.0)
Requires-Dist: pywin32 (>=300,<307) ; python_full_version != "3.8.1" and sys_platform == "win32"
Requires-Dist: robotframework (>=4.0.0,!=4.0.1,!=6.1.0,<7.0.0)
Requires-Dist: robotframework-pythonlibcore (>=4.2.0,<5.0.0)
Requires-Dist: rpaframework-core (>=11.3.1,<12.0.0)
Requires-Dist: uiautomation (>=2.0.15,<3.0.0)
Project-URL: Documentation, https://rpaframework.org/
Project-URL: Repository, https://github.com/robocorp/rpaframework
